Metadata-Version: 2.1
Name: hyperDS
Version: 0.2
Summary: HyperDS is used to store data similar to python representation (like json and xml) and also can store python objects like CLASSES!
Home-page: UNKNOWN
Author: AbdulWahab
Author-email: undeadneon2008@gmail.com
License: MIT
Keywords: pickle
Platform: UNKNOWN
Classifier: License :: OSI Approved :: MIT License
Classifier: Development Status :: 4 - Beta
Classifier: Intended Audience :: Developers
Classifier: Programming Language :: Python :: 3
License-File: LICENSE.md
